rpas/__init__.py
rpas/crypto.py
rpas/fl.py
rpas/pa.py
rpas/proto_xml.py
rpas/restrictions.py
rpas/lib/FlightLog_pb2.py
rpas/lib/PermissionArtefact_pb2.py
rpas/lib/__init__.py
rpas-0.0.1.dist-info/LICENSE
rpas-0.0.1.dist-info/METADATA
rpas-0.0.1.dist-info/WHEEL
rpas-0.0.1.dist-info/top_level.txt
rpas-0.0.1.dist-info/RECORD
