Metadata-Version: 2.1
Name: rpas
Version: 0.0.1
Summary: UNKNOWN
Home-page: UNKNOWN
Author: Abhishek Upperwal
Author-email: rpas@soket.in
License: UNKNOWN
Platform: UNKNOWN
Classifier: Programming Language :: Python :: 3
Classifier: License :: OSI Approved :: MIT License
Classifier: Operating System :: OS Independent
Requires-Dist: protobuf
Requires-Dist: shapely
